src/INTERFACES/UART/RECEIVER/rx_formal_cover/src/uart_receiver.v
module uart_receiver(
	input wire i_CLK,
	input wire i_RX,
	output reg o_RX_DONE,
	output reg [7:0] o_DATA
);

localparam s_IDLE = 0;
localparam s_RX = 1;
localparam s_RX_STOP = 2;

reg [1:0] r_CURRENT_STATE;
reg [1:0] r_NEXT_STATE;

reg [3:0] r_BIT_COUNT;

reg [7:0] r_DATA_REG;

initial begin
	r_CURRENT_STATE = 0;
	r_NEXT_STATE = 0;
	r_BIT_COUNT = 0;
	r_DATA_REG = 0;
end
always@(*)
begin
	case(r_CURRENT_STATE)
		s_IDLE:
		begin
			if(i_RX == 0)
				r_NEXT_STATE = s_RX;
			else
				r_NEXT_STATE = s_IDLE;
		end
		s_RX:
		begin
			if(r_BIT_COUNT == 7)
				r_NEXT_STATE = s_RX_STOP;
			else
				r_NEXT_STATE = s_RX;
		end
		s_RX_STOP:
		begin
			r_NEXT_STATE = s_IDLE;
		end
	endcase
end

always@(posedge i_CLK)
begin
	r_CURRENT_STATE <= r_NEXT_STATE;
end

always@(posedge i_CLK)
begin
	case(r_CURRENT_STATE)
		s_IDLE:
		begin
			r_BIT_COUNT <= 4'd0;
			o_DATA <= 8'b0;
			r_DATA_REG <= 8'd0;
			o_RX_DONE <= 0;
		end
		s_RX:
		begin
			r_BIT_COUNT <= r_BIT_COUNT + 1'b1;
			o_DATA <= 8'b0;
			r_DATA_REG[0] <= i_RX;
			r_DATA_REG <= r_DATA_REG << 1'b1;
			o_RX_DONE <= 0;
		end
		s_RX_STOP:
		begin
			r_BIT_COUNT <= 4'b0;
			o_DATA <= r_DATA_REG;
			r_DATA_REG <= 8'd0;
			o_RX_DONE <= 1;
		end

	endcase
end

`ifdef FORMAL
reg r_PAST_VALID = 0;
always@(posedge i_CLK)
begin
	assume($changed(i_CLK));
	r_PAST_VALID <= 1;
	if(r_PAST_VALID && $rose(i_CLK))
	begin
	assume($changed(i_RX));
		cover(r_CURRENT_STATE == s_IDLE && $past(r_CURRENT_STATE) == s_RX_STOP);
		if($past(r_CURRENT_STATE) == s_IDLE)
		begin
			assert(o_RX_DONE == 0);
			assert(o_DATA == 0);
			assert(r_BIT_COUNT == 0);
		end
		if($past(r_CURRENT_STATE) == s_RX)
		begin
			assert(o_RX_DONE == 0);
		//	assert(r_DATA_REG[0] == $past(i_RX)); //FIXME: 
			assert(o_DATA == 0);
			assert(r_BIT_COUNT == $past(r_BIT_COUNT) + 1);
		end
		if($past(r_CURRENT_STATE) == s_RX_STOP)
		begin
			assert(o_DATA == $past(r_DATA_REG));
			assert(o_RX_DONE == 1);
			assert(r_BIT_COUNT == 0);
		end
	end
end
`endif
endmodule

src/INTERFACES/UART/RECEIVER/rx_formal_cover/engine_0/trace0.vcd
$version Generated by Yosys-SMTBMC $end
$timescale 1ns $end
$var integer 32 t smt_step $end
$var event 1 ! smt_clock $end
$scope module uart_receiver $end
$var wire 1 n0 i_CLK $end
$var wire 1 n1 i_RX $end
$var wire 8 n2 o_DATA $end
$var wire 1 n3 o_RX_DONE $end
$var wire 4 n4 r_BIT_COUNT $end
$var wire 2 n5 r_CURRENT_STATE $end
$var wire 8 n6 r_DATA_REG $end
$var wire 2 n7 r_NEXT_STATE $end
$var wire 1 n8 r_PAST_VALID $end
$upscope $end
$enddefinitions $end
#0
1!
b00000000000000000000000000000000 t
b1 n0
b0 n1
b00000000 n2
b0 n3
b0000 n4
b00 n5
b00000000 n6
b01 n7
b0 n8
#5
#10
1!
b00000000000000000000000000000001 t
b0 n0
b1 n1
b00000000 n2
b0 n3
b0000 n4
b01 n5
b00000000 n6
b01 n7
b1 n8
#15
#20
1!
b00000000000000000000000000000010 t
b1 n0
b0 n1
b00000000 n2
b0 n3
b0001 n4
b01 n5
b00000001 n6
b01 n7
b1 n8
#25
#30
1!
b00000000000000000000000000000011 t
b0 n0
b1 n1
b00000000 n2
b0 n3
b0010 n4
b01 n5
b00000010 n6
b01 n7
b1 n8
#35
#40
1!
b00000000000000000000000000000100 t
b1 n0
b0 n1
b00000000 n2
b0 n3
b0011 n4
b01 n5
b00000101 n6
b01 n7
b1 n8
#45
#50
1!
b00000000000000000000000000000101 t
b0 n0
b0 n1
b00000000 n2
b0 n3
b0100 n4
b01 n5
b00001010 n6
b01 n7
b1 n8
#55
#60
1!
b00000000000000000000000000000110 t
b1 n0
b1 n1
b00000000 n2
b0 n3
b0101 n4
b01 n5
b00010100 n6
b01 n7
b1 n8
#65
#70
1!
b00000000000000000000000000000111 t
b0 n0
b0 n1
b00000000 n2
b0 n3
b0110 n4
b01 n5
b00101001 n6
b01 n7
b1 n8
#75
#80
1!
b00000000000000000000000000001000 t
b1 n0
b1 n1
b00000000 n2
b0 n3
b0111 n4
b01 n5
b01010010 n6
b10 n7
b1 n8
#85
#90
1!
b00000000000000000000000000001001 t
b0 n0
b0 n1
b00000000 n2
b0 n3
b1000 n4
b10 n5
b10100101 n6
b00 n7
b1 n8
#95
#100
1!
b00000000000000000000000000001010 t
b1 n0
b1 n1
b10100101 n2
b1 n3
b0000 n4
b00 n5
b00000000 n6
b00 n7
b1 n8
#105
#110
1!
b00000000000000000000000000001011 t
b0 n0
b0 n1
b00000000 n2
b0 n3
b0000 n4
b00 n5
b00000000 n6
b01 n7
b1 n8
#115
#120
1!
b00000000000000000000000000001100 t
