src/INTERFACES/UART/RECEIVER/uart_receiver.v
module uart_receiver(
	input wire i_CLK,
	input wire i_RESET,
	input wire i_CLK_ENABLE,
	input wire i_RX,
	output reg o_RX_DONE,
	output reg o_FRAMING_ERROR,
	output reg [7:0] o_DATA
);

localparam s_IDLE = 0;
localparam s_RX = 1;
localparam s_RX_STOP = 2;

reg [1:0] r_CURRENT_STATE;
reg [1:0] r_NEXT_STATE;
reg [3:0] r_BIT_COUNT;
reg [7:0] r_DATA_REG;

//TODO:Mux input data reg
initial begin
	r_CURRENT_STATE = 0;
	r_NEXT_STATE = 0;
	r_BIT_COUNT = 0;
	r_DATA_REG = 0;
end
always@(*)
begin
	case(r_CURRENT_STATE)
		s_IDLE:
		begin
			if(!i_RX)
				r_NEXT_STATE = s_RX;
			else
				r_NEXT_STATE = s_IDLE;
		end
		s_RX:
		begin
			if(r_BIT_COUNT == 7)
				r_NEXT_STATE = s_RX_STOP;
			else
				r_NEXT_STATE = s_RX;
		end
		s_RX_STOP:
		begin
			r_NEXT_STATE = s_IDLE;
		end
	endcase
end

always@(posedge i_CLK)
begin
	if(i_RESET)
		r_CURRENT_STATE <= s_IDLE;
	else
	begin
		if(i_CLK_ENABLE)
			r_CURRENT_STATE <= r_NEXT_STATE;
		else
			r_CURRENT_STATE <= r_CURRENT_STATE;
	end
end
//FIXME
always@(posedge i_CLK)
begin
	if(i_RESET)
	begin
		r_BIT_COUNT <= 4'd0;
		r_DATA_REG <= 8'd0;
		o_RX_DONE <= 1'b0;
		o_DATA <= 8'b0;
		o_FRAMING_ERROR <= 1'b0;
	end
	else 
	begin
		if(i_CLK_ENABLE)
		begin

			case(r_CURRENT_STATE)
				s_IDLE:
				begin
					r_BIT_COUNT <= 4'd0;
					r_DATA_REG <= 8'd0;
					o_RX_DONE <= 1'b0;
					o_DATA <= 8'd0;
					o_FRAMING_ERROR <= 1'b0;
				end
				s_RX:
				begin
					r_BIT_COUNT <= r_BIT_COUNT + 1'b1;
					//Bruh. I should not have to do this coercion.
					r_DATA_REG[0] <= i_RX;
					r_DATA_REG[1] <= r_DATA_REG[0];
					r_DATA_REG[2] <= r_DATA_REG[1];
					r_DATA_REG[3] <= r_DATA_REG[2];
					r_DATA_REG[4] <= r_DATA_REG[3];
					r_DATA_REG[5] <= r_DATA_REG[4];
					r_DATA_REG[6] <= r_DATA_REG[5];
					r_DATA_REG[7] <= r_DATA_REG[6];
					o_RX_DONE <= 1'b0;
					o_DATA <= 8'd0;
					o_FRAMING_ERROR <= 1'b0;
				end
				s_RX_STOP:
				begin
					r_BIT_COUNT <= 4'b0;
					r_DATA_REG <= 8'd0;
					o_RX_DONE <= 1'b1;
					//Check if the stop bit is valid
					if(i_RX == 1)
					begin
						o_DATA <= r_DATA_REG;
						o_FRAMING_ERROR <= 1'b0;
					end
					else
					begin
						o_DATA <= 8'd0;
						o_FRAMING_ERROR <= 1'b1;
					end
				end

			endcase
		end
	end
end

`ifdef FORMAL
	reg r_PAST_VALID = 0;
	always@(posedge i_CLK)
	begin
		assume($changed(i_CLK));
		r_PAST_VALID <= 1;
		assume(i_CLK_ENABLE);
		if(r_PAST_VALID && $rose(i_CLK))
		begin
			if($past(i_RESET)) 
			begin
				assert(o_RX_DONE == 0);
				assert(o_DATA == 0);
				assert(o_FRAMING_ERROR == 0);
			end
			else 
			begin
				if($past(i_CLK_ENABLE) == 1)
				begin

					assume($changed(i_RX));

					//Cover return to idle
					cover(r_CURRENT_STATE == s_IDLE && $past(r_CURRENT_STATE) == s_RX_STOP);

					//Check signal outputs.
					if($past(r_CURRENT_STATE) == s_IDLE)
					begin
						assert(o_RX_DONE == 0);
						assert(o_DATA == 0);
						assert(r_BIT_COUNT == 0);
						assert(o_FRAMING_ERROR == 0);
					end
					if($past(r_CURRENT_STATE) == s_RX)
					begin
						assert(o_RX_DONE == 0);
						assert(r_DATA_REG[0] == $past(i_RX));
						assert(o_DATA == 0);
						assert($changed(r_BIT_COUNT));
						assert(o_FRAMING_ERROR == 0);
					end
					if($past(r_CURRENT_STATE) == s_RX_STOP)
					begin
						if($past(i_RX) == 1)
						begin
							assert(o_FRAMING_ERROR == 0);
							assert(o_DATA == $past(r_DATA_REG));
						end
						else
						begin
							assert(o_FRAMING_ERROR == 1);
							assert(o_DATA == 0);
						end
						assert(o_RX_DONE == 1);
						assert(r_BIT_COUNT == 0);
					end

					//Check transition
					if(r_CURRENT_STATE == s_IDLE && i_RX == 0)
						assert(r_NEXT_STATE == s_RX);
					if(r_CURRENT_STATE == s_IDLE && i_RX == 1)
						assert(r_NEXT_STATE == s_IDLE);
					if(r_CURRENT_STATE == s_RX && r_BIT_COUNT != 7)
						assert(r_NEXT_STATE == s_RX);
					if(r_CURRENT_STATE == s_RX && r_BIT_COUNT == 7)
						assert(r_NEXT_STATE == s_RX_STOP);
					if(r_CURRENT_STATE == s_RX_STOP)
						assert(r_NEXT_STATE == s_IDLE);
				end
			end
		end
		if(!$rose(i_CLK))
		begin
			assume($stable(i_RESET));
			assume($stable(i_CLK_ENABLE));
			assume($stable(i_RX));
			//assume($stable(r_CURRENT_STATE));
			//assume($stable(r_NEXT_STATE));
			//assume($stable(r_BIT_COUNT));
			//assume($stable(r_DATA_REG));
		end
	end
`endif
endmodule

src/INTERFACES/UART/RECEIVER/rx_formal_cover/engine_0/trace0.vcd
$version Generated by Yosys-SMTBMC $end
$timescale 1ns $end
$var integer 32 t smt_step $end
$var event 1 ! smt_clock $end
$scope module uart_receiver $end
$var wire 1 n0 i_CLK $end
$var wire 1 n1 i_CLK_ENABLE $end
$var wire 1 n2 i_RESET $end
$var wire 1 n3 i_RX $end
$var wire 8 n4 o_DATA $end
$var wire 1 n5 o_FRAMING_ERROR $end
$var wire 1 n6 o_RX_DONE $end
$var wire 4 n7 r_BIT_COUNT $end
$var wire 2 n8 r_CURRENT_STATE $end
$var wire 8 n9 r_DATA_REG $end
$var wire 2 n10 r_NEXT_STATE $end
$var wire 1 n11 r_PAST_VALID $end
$upscope $end
$enddefinitions $end
#0
1!
b00000000000000000000000000000000 t
b1 n0
b1 n1
b0 n2
b0 n3
b00000100 n4
b0 n5
b0 n6
b0000 n7
b00 n8
b00000000 n9
b01 n10
b0 n11
#5
#10
1!
b00000000000000000000000000000001 t
b0 n0
b1 n1
b0 n2
b0 n3
b00000000 n4
b0 n5
b0 n6
b0000 n7
b01 n8
b00000000 n9
b01 n10
b1 n11
#15
#20
1!
b00000000000000000000000000000010 t
b1 n0
b1 n1
b0 n2
b1 n3
b00000000 n4
b0 n5
b0 n6
b0001 n7
b01 n8
b00000000 n9
b01 n10
b1 n11
#25
#30
1!
b00000000000000000000000000000011 t
b0 n0
b1 n1
b0 n2
b1 n3
b00000000 n4
b0 n5
b0 n6
b0010 n7
b01 n8
b00000001 n9
b01 n10
b1 n11
#35
#40
1!
b00000000000000000000000000000100 t
b1 n0
b1 n1
b0 n2
b0 n3
b00000000 n4
b0 n5
b0 n6
b0011 n7
b01 n8
b00000011 n9
b01 n10
b1 n11
#45
#50
1!
b00000000000000000000000000000101 t
b0 n0
b1 n1
b0 n2
b0 n3
b00000000 n4
b0 n5
b0 n6
b0100 n7
b01 n8
b00000110 n9
b01 n10
b1 n11
#55
#60
1!
b00000000000000000000000000000110 t
b1 n0
b1 n1
b0 n2
b1 n3
b00000000 n4
b0 n5
b0 n6
b0101 n7
b01 n8
b00001100 n9
b01 n10
b1 n11
#65
#70
1!
b00000000000000000000000000000111 t
b0 n0
b1 n1
b0 n2
b1 n3
b00000000 n4
b0 n5
b0 n6
b0110 n7
b01 n8
b00011001 n9
b01 n10
b1 n11
#75
#80
1!
b00000000000000000000000000001000 t
b1 n0
b1 n1
b0 n2
b0 n3
b00000000 n4
b0 n5
b0 n6
b0111 n7
b01 n8
b00110011 n9
b10 n10
b1 n11
#85
#90
1!
b00000000000000000000000000001001 t
b0 n0
b1 n1
b0 n2
b1 n3
b00000000 n4
b0 n5
b0 n6
b1000 n7
b10 n8
b01100110 n9
b00 n10
b1 n11
#95
#100
1!
b00000000000000000000000000001010 t
b1 n0
b0 n1
b1 n2
b0 n3
b01100110 n4
b0 n5
b1 n6
b0000 n7
b00 n8
b00000000 n9
b01 n10
b1 n11
#105
#110
1!
b00000000000000000000000000001011 t
b0 n0
b0 n1
b1 n2
b1 n3
b00000000 n4
b0 n5
b0 n6
b0000 n7
b00 n8
b00000000 n9
b00 n10
b1 n11
#115
#120
1!
b00000000000000000000000000001100 t
