src/INTERFACES/UART/TRANSMITTER/uart_transmitter.v
module uart_transmitter (
	input wire i_CLK,
	input wire i_RESET,
	input wire i_CLK_EN,
	input wire i_TX_ENABLE,
	input wire [7:0] i_DATA_IN,
	output reg o_TX_BUSY,
	output reg o_TX
);

localparam s_IDLE 	= 2'd0;
localparam s_START_TX 	= 2'd1;
localparam s_TRANSMIT 	= 2'd2;
localparam s_STOP_TX 	= 2'd3;

reg [1:0] r_CURRENT_STATE;
reg [1:0] r_NEXT_STATE;
reg [2:0] r_BIT_COUNT;
reg [7:0] r_DATA_REG;

initial 
begin
	r_CURRENT_STATE = 2'd0;
	r_NEXT_STATE 	= 2'd0;
	r_BIT_COUNT 	= 3'd0;
	r_DATA_REG 	= 8'd0;
end

always@(*)
begin
	case(r_CURRENT_STATE)
		s_IDLE:
		begin
			r_NEXT_STATE = (i_TX_ENABLE) ? s_START_TX : s_IDLE;
		end
		s_START_TX:
			r_NEXT_STATE = s_TRANSMIT;
		s_TRANSMIT:
		begin
			r_NEXT_STATE = (r_BIT_COUNT == 3'd7) ? s_STOP_TX : s_TRANSMIT;
		end
		s_STOP_TX:
			r_NEXT_STATE = s_IDLE;

	endcase
end

always@(posedge i_CLK)
begin
	if(i_RESET)
		r_CURRENT_STATE <= s_IDLE;
	else
	begin
		if(i_CLK_EN)
			r_CURRENT_STATE <= r_NEXT_STATE;
		else
			r_CURRENT_STATE <= r_CURRENT_STATE;
	end
end

always@(*)
begin
	o_TX_BUSY = |r_CURRENT_STATE;
	case(r_CURRENT_STATE)
		s_IDLE:
		begin
			o_TX = 1'b1;
		end
		s_START_TX:
		begin
			o_TX = 1'b0;
		end
		s_TRANSMIT:
		begin
			o_TX = r_DATA_REG[r_BIT_COUNT];
		end
		s_STOP_TX:
		begin
			o_TX = 1'b1;
		end
	endcase
end

always@(posedge i_CLK)
begin
	if(r_CURRENT_STATE == s_IDLE)
		r_DATA_REG <= i_DATA_IN;
	else
		r_DATA_REG <= r_DATA_REG;

	if(r_CURRENT_STATE == s_TRANSMIT)
		r_BIT_COUNT <= r_BIT_COUNT + 1'b1;
	else
		r_BIT_COUNT <= 3'd0;
end

`ifdef FORMAL
	reg f_PAST_VALID = 0;
	reg [7:0] f_TX_DATA = 0;
	always@(posedge i_CLK)
	begin
		f_PAST_VALID <= 1;
		assume($changed(i_CLK));
		if(f_PAST_VALID && $rose(i_CLK))
		begin
			if($past(i_RESET) == 1)
			begin
				assert(o_TX == 1);
				assert(o_TX_BUSY == 0);
				assert(r_CURRENT_STATE == s_IDLE);
				assert(r_BIT_COUNT == 0);
				assert(r_DATA_REG == $past(i_DATA_IN));
			end
			else
			begin
				if($past(i_CLK_EN)) begin
					cover(r_CURRENT_STATE == s_IDLE && $past(r_CURRENT_STATE) == s_STOP_TX);

					if(r_CURRENT_STATE == s_IDLE)
						assert(o_TX);
					else if(r_CURRENT_STATE == s_START_TX)
						assert(!o_TX);
					else if(r_CURRENT_STATE == s_TRANSMIT)
						assert(o_TX == r_DATA_REG[r_BIT_COUNT]);
					else
						assert(o_TX);
					if(r_CURRENT_STATE != s_IDLE)
						assert(o_TX_BUSY);
					else
						assert(!o_TX_BUSY);
					//Transitions
					if($past(r_CURRENT_STATE) == s_START_TX)
						assert(r_CURRENT_STATE == s_TRANSMIT);
					if($past(r_CURRENT_STATE) == s_STOP_TX)
						assert(r_CURRENT_STATE == s_IDLE);
					if(r_CURRENT_STATE == s_STOP_TX)
						assert(r_NEXT_STATE == s_IDLE);
					if(r_CURRENT_STATE == s_START_TX)
						assert(r_NEXT_STATE == s_TRANSMIT);



					if($past(r_CURRENT_STATE) == s_TRANSMIT && r_NEXT_STATE == s_STOP_TX)
					begin
						assert($changed(r_BIT_COUNT));
						assert(r_BIT_COUNT == $past(r_BIT_COUNT) + 1);
					end
					if(r_CURRENT_STATE == s_START_TX && f_PAST_VALID)
						assert(r_DATA_REG == $past(i_DATA_IN));
				end
			end
		end
		if(f_PAST_VALID && !$rose(i_CLK))
		begin
			assume($stable(i_RESET));
			assume($stable(i_TX_ENABLE));
			assume($stable(i_DATA_IN));
		end

	end
`endif
endmodule

src/INTERFACES/UART/TRANSMITTER/tx_formal_cover/engine_0/trace0.vcd
$version Generated by Yosys-SMTBMC $end
$timescale 1ns $end
$var integer 32 t smt_step $end
$var event 1 ! smt_clock $end
$scope module uart_transmitter $end
$var wire 1 n0 f_PAST_VALID $end
$var wire 8 n1 f_TX_DATA $end
$var wire 1 n2 i_CLK $end
$var wire 1 n3 i_CLK_EN $end
$var wire 8 n4 i_DATA_IN $end
$var wire 1 n5 i_RESET $end
$var wire 1 n6 i_TX_ENABLE $end
$var wire 1 n7 o_TX $end
$var wire 1 n8 o_TX_BUSY $end
$var wire 3 n9 r_BIT_COUNT $end
$var wire 2 n10 r_CURRENT_STATE $end
$var wire 8 n11 r_DATA_REG $end
$var wire 2 n12 r_NEXT_STATE $end
$upscope $end
$enddefinitions $end
#0
1!
b00000000000000000000000000000000 t
b0 n0
b00000000 n1
b0 n2
b1 n3
b10000000 n4
b0 n5
b1 n6
b1 n7
b0 n8
b000 n9
b00 n10
b00000000 n11
b01 n12
#5
#10
1!
b00000000000000000000000000000001 t
b1 n0
b00000000 n1
b1 n2
b1 n3
b10000000 n4
b0 n5
b1 n6
b0 n7
b1 n8
b000 n9
b01 n10
b10000000 n11
b10 n12
#15
#20
1!
b00000000000000000000000000000010 t
b1 n0
b00000000 n1
b0 n2
b1 n3
b10000000 n4
b0 n5
b1 n6
b0 n7
b1 n8
b000 n9
b10 n10
b10000000 n11
b10 n12
#25
#30
1!
b00000000000000000000000000000011 t
b1 n0
b00000000 n1
b1 n2
b1 n3
b10000000 n4
b0 n5
b1 n6
b0 n7
b1 n8
b001 n9
b10 n10
b10000000 n11
b10 n12
#35
#40
1!
b00000000000000000000000000000100 t
b1 n0
b00000000 n1
b0 n2
b0 n3
b10000000 n4
b0 n5
b1 n6
b0 n7
b1 n8
b010 n9
b10 n10
b10000000 n11
b10 n12
#45
#50
1!
b00000000000000000000000000000101 t
b1 n0
b00000000 n1
b1 n2
b1 n3
b10000000 n4
b0 n5
b0 n6
b0 n7
b1 n8
b011 n9
b10 n10
b10000000 n11
b10 n12
#55
#60
1!
b00000000000000000000000000000110 t
b1 n0
b00000000 n1
b0 n2
b1 n3
b10000000 n4
b0 n5
b0 n6
b0 n7
b1 n8
b100 n9
b10 n10
b10000000 n11
b10 n12
#65
#70
1!
b00000000000000000000000000000111 t
b1 n0
b00000000 n1
b1 n2
b1 n3
b10000000 n4
b0 n5
b0 n6
b0 n7
b1 n8
b101 n9
b10 n10
b10000000 n11
b10 n12
#75
#80
1!
b00000000000000000000000000001000 t
b1 n0
b00000000 n1
b0 n2
b0 n3
b10000000 n4
b0 n5
b0 n6
b0 n7
b1 n8
b110 n9
b10 n10
b10000000 n11
b10 n12
#85
#90
1!
b00000000000000000000000000001001 t
b1 n0
b00000000 n1
b1 n2
b1 n3
b10000000 n4
b0 n5
b0 n6
b1 n7
b1 n8
b111 n9
b10 n10
b10000000 n11
b11 n12
#95
#100
1!
b00000000000000000000000000001010 t
b1 n0
b00000000 n1
b0 n2
b1 n3
b10000000 n4
b0 n5
b0 n6
b1 n7
b1 n8
b000 n9
b11 n10
b10000000 n11
b00 n12
#105
#110
1!
b00000000000000000000000000001011 t
b1 n0
b00000000 n1
b1 n2
b0 n3
b10000000 n4
b0 n5
b0 n6
b1 n7
b0 n8
b000 n9
b00 n10
b10000000 n11
b00 n12
#115
#120
1!
b00000000000000000000000000001100 t
b1 n0
b00000000 n1
b0 n2
b0 n3
b10000000 n4
b0 n5
b0 n6
b1 n7
b0 n8
b000 n9
b00 n10
b10000000 n11
b00 n12
#125
#130
1!
b00000000000000000000000000001101 t
