src/INTERFACES/UART/SIMPLEX/uart_simplex.v
module uart_simplex (
	input wire i_CLK,
	input wire [7:0] i_DATA_IN,
	input wire i_TX_ENABLE,
	output reg o_TX
);

reg [8:0] r_TX_REG = 0;
reg [3:0] r_BIT_COUNT = 0;

reg r_CURRENT_STATE = s_IDLE;
reg r_NEXT_STATE;

localparam s_IDLE = 0;
localparam s_TX = 1;

always@(*)
begin
	case(r_CURRENT_STATE)
		s_IDLE:
		begin
			o_TX = 1;
			if(i_TX_ENABLE == 1)
				r_NEXT_STATE = s_TX;
			else
				r_NEXT_STATE = s_IDLE;
		end
		s_TX:
		begin
			o_TX = r_TX_REG[0];//move this to a comb block
			if(r_BIT_COUNT == 7)
				r_NEXT_STATE = s_IDLE;
			else
				r_NEXT_STATE = s_TX;
		end
	endcase

end

always@(posedge i_CLK)
begin
	r_CURRENT_STATE <= r_NEXT_STATE;
	case(r_CURRENT_STATE)//Maybe use next state.
		s_IDLE:
	begin
		r_BIT_COUNT <= 0;
		r_TX_REG <= {i_DATA_IN,1'b0};
	end
	s_TX:
	begin
		r_BIT_COUNT <= r_BIT_COUNT + 1;
		r_TX_REG <= r_TX_REG >> 1;
	end
endcase

end


//TODO: FIX THIS
`ifdef FORMAL
	reg r_PAST_VALID = 0;
	initial begin
		assume(i_TX_ENABLE == 0);
	end
	always@(posedge i_CLK)
	begin
		r_PAST_VALID <= 1;
		assume($changed(i_CLK));
		assume(i_DATA_IN == 8'b00101010);
		if(r_PAST_VALID == 1 && $rose(i_CLK))
		begin
			cover($past(r_CURRENT_STATE) == s_TX && r_CURRENT_STATE == s_IDLE);
			if($past(r_CURRENT_STATE) == s_IDLE)
			begin
				assert(r_BIT_COUNT == 0);
			end
			if($past(r_CURRENT_STATE) == s_TX)
			begin
			//	assert(o_TX == $past(r_TX_REG[0]));
			//	assert(r_TX_REG == $past(r_TX_REG) >> 1);
			end
		end
	end
`endif



endmodule

src/INTERFACES/UART/SIMPLEX/us/engine_0/trace0.vcd
$version Generated by Yosys-SMTBMC $end
$timescale 1ns $end
$var integer 32 t smt_step $end
$var event 1 ! smt_clock $end
$scope module uart_simplex $end
$var wire 1 n0 i_CLK $end
$var wire 8 n1 i_DATA_IN $end
$var wire 1 n2 i_TX_ENABLE $end
$var wire 1 n3 o_TX $end
$var wire 4 n4 r_BIT_COUNT $end
$var wire 1 n5 r_CURRENT_STATE $end
$var wire 1 n6 r_NEXT_STATE $end
$var wire 1 n7 r_PAST_VALID $end
$var wire 9 n8 r_TX_REG $end
$upscope $end
$enddefinitions $end
#0
1!
b00000000000000000000000000000000 t
b1 n0
b00101010 n1
b0 n2
b1 n3
b0000 n4
b0 n5
b0 n6
b0 n7
b000000000 n8
#5
#10
1!
b00000000000000000000000000000001 t
b0 n0
b00101010 n1
b1 n2
b1 n3
b0000 n4
b0 n5
b1 n6
b1 n7
b001010100 n8
#15
#20
1!
b00000000000000000000000000000010 t
b1 n0
b00101010 n1
b0 n2
b0 n3
b0000 n4
b1 n5
b1 n6
b1 n7
b001010100 n8
#25
#30
1!
b00000000000000000000000000000011 t
b0 n0
b00101010 n1
b0 n2
b0 n3
b0001 n4
b1 n5
b1 n6
b1 n7
b000101010 n8
#35
#40
1!
b00000000000000000000000000000100 t
b1 n0
b00101010 n1
b0 n2
b1 n3
b0010 n4
b1 n5
b1 n6
b1 n7
b000010101 n8
#45
#50
1!
b00000000000000000000000000000101 t
b0 n0
b00101010 n1
b0 n2
b0 n3
b0011 n4
b1 n5
b1 n6
b1 n7
b000001010 n8
#55
#60
1!
b00000000000000000000000000000110 t
b1 n0
b00101010 n1
b0 n2
b1 n3
b0100 n4
b1 n5
b1 n6
b1 n7
b000000101 n8
#65
#70
1!
b00000000000000000000000000000111 t
b0 n0
b00101010 n1
b0 n2
b0 n3
b0101 n4
b1 n5
b1 n6
b1 n7
b000000010 n8
#75
#80
1!
b00000000000000000000000000001000 t
b1 n0
b00101010 n1
b0 n2
b1 n3
b0110 n4
b1 n5
b1 n6
b1 n7
b000000001 n8
#85
#90
1!
b00000000000000000000000000001001 t
b0 n0
b00101010 n1
b0 n2
b0 n3
b0111 n4
b1 n5
b0 n6
b1 n7
b000000000 n8
#95
#100
1!
b00000000000000000000000000001010 t
b1 n0
b00101010 n1
b0 n2
b1 n3
b1000 n4
b0 n5
b0 n6
b1 n7
b000000000 n8
#105
#110
1!
b00000000000000000000000000001011 t
b0 n0
b00101010 n1
b0 n2
b1 n3
b0000 n4
b0 n5
b0 n6
b1 n7
b001010100 n8
#115
#120
1!
b00000000000000000000000000001100 t
