src/INTERFACES/UART/TRANSMITTER/uart_transmitter.v
module uart_transmitter (
	input wire i_CLK,
	input wire i_CLK_ENABLE,
	input wire i_TX_ENABLE,
	input wire [7:0] i_DATA_IN,
	output reg  o_TX_BUSY,
	output reg o_TX
);

localparam s_IDLE = 0;
localparam s_START_TX = 1;
localparam s_TRANSMIT = 2;
localparam s_STOP_TX = 3;

reg [1:0] r_CURRENT_STATE;
reg [1:0] r_NEXT_STATE;
reg [3:0] r_BIT_COUNT;
reg [7:0] r_DATA_REG;

initial begin
	r_CURRENT_STATE = 0;
	r_NEXT_STATE = 0;
	r_BIT_COUNT = 0;
	r_DATA_REG = 0;
end
always@(*)
begin
	case(r_CURRENT_STATE)
		s_IDLE:
		begin
			if(i_TX_ENABLE == 1)
				r_NEXT_STATE = s_START_TX;
			else
				r_NEXT_STATE = s_IDLE;
		end
		s_START_TX:
			r_NEXT_STATE = s_TRANSMIT;
		s_TRANSMIT:
		begin
			if(r_BIT_COUNT == 8)
				r_NEXT_STATE = s_STOP_TX;
			else
				r_NEXT_STATE = s_TRANSMIT;
		end
		s_STOP_TX:
			r_NEXT_STATE = s_IDLE;

	endcase
end

always@(posedge i_CLK)
begin
	if(i_CLK_ENABLE == 1)
		r_CURRENT_STATE <= r_NEXT_STATE;
	else
		r_CURRENT_STATE <= r_CURRENT_STATE;
end

always@(posedge i_CLK)
begin
	if(r_CURRENT_STATE == s_TRANSMIT && i_CLK_ENABLE == 1)
		r_BIT_COUNT <= r_BIT_COUNT + 1'b1;
	else
		r_BIT_COUNT <= 4'd0;
end

always@(posedge i_CLK)
begin
	if(i_CLK_ENABLE == 1) //BAUD rate will be external
	begin
		case(r_CURRENT_STATE)
			s_IDLE:
			begin
				r_DATA_REG <= i_DATA_IN;
				o_TX <= 1'b1;
				o_TX_BUSY <= 1'b0;
			end
			s_START_TX:
			begin
				r_DATA_REG <= r_DATA_REG;
				o_TX <= 1'b0;
				o_TX_BUSY <= 1'b1;
			end
			s_TRANSMIT:
			begin
				r_DATA_REG <= r_DATA_REG >> 1'b1;
				o_TX_BUSY <= 1'b1;
				if(r_BIT_COUNT != 8)
					o_TX <= r_DATA_REG[0];
				else
					o_TX <= 1'b1;
			end
			s_STOP_TX:
			begin
				o_TX_BUSY <= 1'b1;
				r_DATA_REG <= r_DATA_REG;
				o_TX <= 1'b1;
			end
		endcase
	end
end

`ifdef FORMAL
	reg r_PAST_VALID = 0;
	always@(posedge i_CLK)
	begin
		assume(i_CLK_ENABLE == 1);
		assume($changed(i_CLK));
		r_PAST_VALID <= 1;
		if(r_PAST_VALID && $rose(i_CLK)) begin
			//cover transiton back to idle
			cover(r_CURRENT_STATE == s_IDLE && $past(r_CURRENT_STATE == s_STOP_TX));

			//Check state assertions
			if($past(r_CURRENT_STATE) == s_IDLE)
			begin
				assert(o_TX_BUSY == 0);
				assert(o_TX == 1);
				assert(r_BIT_COUNT == 3'd0);
			end
			if($past(r_CURRENT_STATE) == s_START_TX) 
			begin
				assert(o_TX_BUSY == 1);
				assert(o_TX == 0);
				assert(r_BIT_COUNT == 0);
			end
			if($past(r_CURRENT_STATE) == s_TRANSMIT)
			begin
				if(r_BIT_COUNT != 9)
					assert(o_TX == $past(r_DATA_REG[0]));
				else
					assert(o_TX == 1);
				assert(o_TX_BUSY == 1);
				assert(r_BIT_COUNT == $past(r_BIT_COUNT) + 1);
			end
			if($past(r_CURRENT_STATE) == s_STOP_TX)
			begin
				assert(o_TX_BUSY == 1);
				assert(o_TX == 1);
				assert($past(r_BIT_COUNT) == 9);
			end

			//Check transitions
			if(i_TX_ENABLE == 1 && r_CURRENT_STATE == s_IDLE)
				assert(r_NEXT_STATE == s_START_TX);
			if(i_TX_ENABLE == 0 && r_CURRENT_STATE == s_IDLE)
				assert(r_NEXT_STATE == s_IDLE);
			if(r_CURRENT_STATE == s_START_TX)
				assert(r_NEXT_STATE == s_TRANSMIT);
			if(r_CURRENT_STATE == s_TRANSMIT && r_BIT_COUNT != 8)
				assert(r_NEXT_STATE == s_TRANSMIT);
			if(r_CURRENT_STATE == s_TRANSMIT && r_BIT_COUNT == 8)
				assert(r_NEXT_STATE == s_STOP_TX);
			if(r_CURRENT_STATE == s_STOP_TX)
				assert(r_NEXT_STATE == s_IDLE);
		end
	end
`endif
endmodule

src/INTERFACES/UART/TRANSMITTER/tx_formal_cover/engine_1/trace0.vcd
$version Generated by Yosys-SMTBMC $end
$timescale 1ns $end
$var integer 32 t smt_step $end
$var event 1 ! smt_clock $end
$scope module uart_transmitter $end
$var wire 1 n0 i_CLK $end
$var wire 1 n1 i_CLK_ENABLE $end
$var wire 8 n2 i_DATA_IN $end
$var wire 1 n3 i_TX_ENABLE $end
$var wire 1 n4 o_TX $end
$var wire 1 n5 o_TX_BUSY $end
$var wire 4 n6 r_BIT_COUNT $end
$var wire 2 n7 r_CURRENT_STATE $end
$var wire 8 n8 r_DATA_REG $end
$var wire 2 n9 r_NEXT_STATE $end
$var wire 1 n10 r_PAST_VALID $end
$upscope $end
$enddefinitions $end
#0
1!
b00000000000000000000000000000000 t
b0 n0
b1 n1
b00000000 n2
b0 n3
b0 n4
b1 n5
b0000 n6
b00 n7
b00000000 n8
b00 n9
b0 n10
#5
#10
1!
b00000000000000000000000000000001 t
b1 n0
b1 n1
b00001001 n2
b1 n3
b1 n4
b0 n5
b0000 n6
b00 n7
b00000000 n8
b01 n9
b1 n10
#15
#20
1!
b00000000000000000000000000000010 t
b0 n0
b1 n1
b00000000 n2
b0 n3
b1 n4
b0 n5
b0000 n6
b01 n7
b00001001 n8
b10 n9
b1 n10
#25
#30
1!
b00000000000000000000000000000011 t
b1 n0
b1 n1
b00000100 n2
b0 n3
b0 n4
b1 n5
b0000 n6
b10 n7
b00001001 n8
b10 n9
b1 n10
#35
#40
1!
b00000000000000000000000000000100 t
b0 n0
b1 n1
b00000001 n2
b0 n3
b1 n4
b1 n5
b0001 n6
b10 n7
b00000100 n8
b10 n9
b1 n10
#45
#50
1!
b00000000000000000000000000000101 t
b1 n0
b1 n1
b00000001 n2
b0 n3
b0 n4
b1 n5
b0010 n6
b10 n7
b00000010 n8
b10 n9
b1 n10
#55
#60
1!
b00000000000000000000000000000110 t
b0 n0
b1 n1
b00000000 n2
b0 n3
b0 n4
b1 n5
b0011 n6
b10 n7
b00000001 n8
b10 n9
b1 n10
#65
#70
1!
b00000000000000000000000000000111 t
b1 n0
b1 n1
b00000000 n2
b0 n3
b1 n4
b1 n5
b0100 n6
b10 n7
b00000000 n8
b10 n9
b1 n10
#75
#80
1!
b00000000000000000000000000001000 t
b0 n0
b1 n1
b00000000 n2
b0 n3
b0 n4
b1 n5
b0101 n6
b10 n7
b00000000 n8
b10 n9
b1 n10
#85
#90
1!
b00000000000000000000000000001001 t
b1 n0
b1 n1
b00000000 n2
b0 n3
b0 n4
b1 n5
b0110 n6
b10 n7
b00000000 n8
b10 n9
b1 n10
#95
#100
1!
b00000000000000000000000000001010 t
b0 n0
b1 n1
b00000000 n2
b0 n3
b0 n4
b1 n5
b0111 n6
b10 n7
b00000000 n8
b10 n9
b1 n10
#105
#110
1!
b00000000000000000000000000001011 t
b1 n0
b1 n1
b01000000 n2
b1 n3
b0 n4
b1 n5
b1000 n6
b10 n7
b00000000 n8
b11 n9
b1 n10
#115
#120
1!
b00000000000000000000000000001100 t
b0 n0
b1 n1
b01000000 n2
b0 n3
b1 n4
b1 n5
b1001 n6
b11 n7
b00000000 n8
b00 n9
b1 n10
#125
#130
1!
b00000000000000000000000000001101 t
b1 n0
b1 n1
b00000000 n2
b1 n3
b1 n4
b1 n5
b0000 n6
b00 n7
b00000000 n8
b01 n9
b1 n10
#135
#140
1!
b00000000000000000000000000001110 t
b0 n0
b1 n1
b00000000 n2
b0 n3
b1 n4
b0 n5
b0000 n6
b01 n7
b00000000 n8
b10 n9
b1 n10
#145
#150
1!
b00000000000000000000000000001111 t
