src/INTERFACES/UART/TRANSMITTER/uart_transmitter.v
module uart_transmitter (
	input wire i_CLK,
	input wire i_RESET,
	input wire i_TX_ENABLE,
	input wire [7:0] i_DATA_IN,
	output reg o_TX_BUSY,
	output reg o_TX
);

localparam s_IDLE 	= 2'd0;
localparam s_START_TX 	= 2'd1;
localparam s_TRANSMIT 	= 2'd2;
localparam s_STOP_TX 	= 2'd3;

//localparam lp_CLOCKS_PER_BAUD = 100_000_000 / 115200;
localparam lp_CLOCKS_PER_BAUD = 1;

reg [1:0] r_CURRENT_STATE;
reg [1:0] r_NEXT_STATE;
reg [2:0] r_BIT_COUNT;
reg [31:0] r_BAUD_COUNTER;
reg [7:0] r_DATA_REG;
reg r_STATE_CHANGE_EN;

initial 
begin
	r_CURRENT_STATE = 2'd0;
	r_NEXT_STATE 	= 2'd0;
	r_BIT_COUNT 	= 3'd0;
	r_DATA_REG 	= 8'd0;
	r_BAUD_COUNTER  = 32'd0;
	r_STATE_CHANGE_EN = 0;
end

//FIXME: something in the block causes induction and cover to fail.
always@(posedge i_CLK)
begin
	if(i_RESET)
	begin
		r_STATE_CHANGE_EN <= 0;
		r_BAUD_COUNTER <= 0;
	end
	else 
	begin
		if(r_BAUD_COUNTER == lp_CLOCKS_PER_BAUD)
		begin
			r_STATE_CHANGE_EN <= 1;
			r_BAUD_COUNTER <= 0;
		end
		else
		begin
			r_STATE_CHANGE_EN <= 0;
			r_BAUD_COUNTER <= r_BAUD_COUNTER + 1;
		end
	end

end
always@(*)
begin
	case(r_CURRENT_STATE)
		s_IDLE:
		begin
			if(i_TX_ENABLE == 1'b1)
				r_NEXT_STATE = s_START_TX;
			else
				r_NEXT_STATE = s_IDLE;
		end
		s_START_TX:
			r_NEXT_STATE = s_TRANSMIT;
		s_TRANSMIT:
		begin
			if(r_BIT_COUNT == 3'd7)
				r_NEXT_STATE = s_STOP_TX;
			else
				r_NEXT_STATE = s_TRANSMIT;
		end
		s_STOP_TX:
			r_NEXT_STATE = s_IDLE;

	endcase
end

always@(posedge i_CLK)
begin
	if(i_RESET == 1'b1)
		r_CURRENT_STATE <= s_IDLE;
	else
	begin
		r_CURRENT_STATE <= r_NEXT_STATE;
	end
end

always@(posedge i_CLK)
begin
	if(r_CURRENT_STATE == s_TRANSMIT && r_STATE_CHANGE_EN)
		r_BIT_COUNT <= r_BIT_COUNT + 1'b1;
	else
		r_BIT_COUNT <= 3'd0;
end

always@(posedge i_CLK)
begin
	case(r_CURRENT_STATE)
		s_IDLE:
		begin
			r_DATA_REG <= i_DATA_IN;
			o_TX <= 1'b1;
			o_TX_BUSY <= 1'b0;
		end
		s_START_TX:
		begin
			r_DATA_REG <= r_DATA_REG;
			o_TX <= 1'b0;
			o_TX_BUSY <= 1'b1;
		end
		s_TRANSMIT:
		begin
			r_DATA_REG <= r_DATA_REG;
			o_TX <= r_DATA_REG[r_BIT_COUNT];
			o_TX_BUSY <= 1'b1;
		end
		s_STOP_TX:
		begin
			r_DATA_REG <= r_DATA_REG;
			o_TX <= 1'b1;
			o_TX_BUSY <= 1'b0;
		end
	endcase
end

`ifdef FORMAL
	reg f_PAST_VALID = 0;
	(*any_const*)	reg [7:0] f_TX_DATA = 0;
	(*any_const*)	reg [3:0] f_TX_COUNTER = 0;
	always@(posedge i_CLK)
	begin
		assert(f_TX_COUNTER <= 9);
		if($past(r_CURRENT_STATE) == s_IDLE && $past(i_TX_ENABLE))
			f_TX_DATA <= i_DATA_IN;
		else
			assume($stable(f_TX_DATA));

		if(($past(r_CURRENT_STATE) == s_START_TX || $past(r_CURRENT_STATE) == s_TRANSMIT || $past(r_CURRENT_STATE) == s_STOP_TX) && $rose(i_CLK) && r_STATE_CHANGE_EN)
			f_TX_COUNTER <= f_TX_COUNTER + 1;
		else if(r_CURRENT_STATE == s_IDLE && $rose(i_CLK))
			f_TX_COUNTER <= 0;
		else
			assume($stable(f_TX_COUNTER));
	end

	always@(posedge i_CLK)
	begin
		if($past(r_CURRENT_STATE) == s_TRANSMIT && $rose(i_CLK) && r_STATE_CHANGE_EN)
		begin
			assert(f_TX_DATA[r_BIT_COUNT] == r_DATA_REG[r_BIT_COUNT]);
			assert($changed(r_BIT_COUNT));
			assert(r_BIT_COUNT == $past(r_BIT_COUNT) + 1);
		end
		if(r_CURRENT_STATE == s_START_TX)
			assert(r_DATA_REG == $past(i_DATA_IN));

	end
	always@(posedge i_CLK)
	begin
		f_PAST_VALID <= 1;
		assume($changed(i_CLK));
		if(f_PAST_VALID && $rose(i_CLK))
		begin
			if($past(i_RESET) == 1)
			begin
				assert(o_TX == 1);
				assert(o_TX_BUSY == 0);
				assert(r_CURRENT_STATE == s_IDLE);
				assert(r_BIT_COUNT == 0);
				assert(r_DATA_REG == $past(i_DATA_IN));
				assert(r_BAUD_COUNTER == 0);
				assert(r_STATE_CHANGE_EN == 0);
			end
			else
			begin
				cover(r_CURRENT_STATE == s_IDLE && $past(r_CURRENT_STATE) == s_STOP_TX);

				if($past(r_CURRENT_STATE) == s_IDLE)
					assert(o_TX);
				else if($past(r_CURRENT_STATE) == s_START_TX)
					assert(!o_TX);
				else if($past(r_CURRENT_STATE) == s_TRANSMIT)
					assert(o_TX == f_TX_DATA[r_BIT_COUNT]);
				else
					assert(o_TX);
				if($past(r_CURRENT_STATE) != s_IDLE)
					assert(o_TX_BUSY);
				else
					assert(!o_TX_BUSY);
				if($past(r_CURRENT_STATE) == s_START_TX || $past(r_CURRENT_STATE) == s_TRANSMIT || $past(r_CURRENT_STATE) == s_STOP_TX)
				begin
					assert(r_BAUD_COUNTER == $past(r_BAUD_COUNTER) + 1);
					if($past(r_BAUD_COUNTER) == lp_CLOCKS_PER_BAUD)
					begin
						assert(r_STATE_CHANGE_EN);
						assert(r_BAUD_COUNTER == 0);
					end
					else
					begin
						assert(!r_STATE_CHANGE_EN);
						assert($changed(r_BAUD_COUNTER));
					end
				end

				//Transitions
				if($past(r_CURRENT_STATE) == s_START_TX)
					assert(r_CURRENT_STATE == s_TRANSMIT);
				if($past(r_CURRENT_STATE) == s_STOP_TX)
					assert(r_CURRENT_STATE == s_IDLE);
				if(r_CURRENT_STATE == s_STOP_TX)
					assert(r_NEXT_STATE == s_IDLE);
				if(r_CURRENT_STATE == s_START_TX)
					assert(r_NEXT_STATE == s_TRANSMIT);
			end
		end
		if(f_PAST_VALID && !$rose(i_CLK))
		begin
			assume($stable(i_RESET));
			assume($stable(i_TX_ENABLE));
			assume($stable(i_DATA_IN));
		end

	end
`endif
endmodule

src/INTERFACES/UART/TRANSMITTER/tx_formal_prove/engine_0/trace_induct.vcd
$version Generated by Yosys-SMTBMC $end
$timescale 1ns $end
$var integer 32 t smt_step $end
$var event 1 ! smt_clock $end
$scope module uart_transmitter $end
$var wire 1 n0 f_PAST_VALID $end
$var wire 4 n1 f_TX_COUNTER $end
$var wire 8 n2 f_TX_DATA $end
$var wire 1 n3 i_CLK $end
$var wire 8 n4 i_DATA_IN $end
$var wire 1 n5 i_RESET $end
$var wire 1 n6 i_TX_ENABLE $end
$var wire 1 n7 o_TX $end
$var wire 1 n8 o_TX_BUSY $end
$var wire 32 n9 r_BAUD_COUNTER $end
$var wire 3 n10 r_BIT_COUNT $end
$var wire 2 n11 r_CURRENT_STATE $end
$var wire 8 n12 r_DATA_REG $end
$var wire 2 n13 r_NEXT_STATE $end
$var wire 1 n14 r_STATE_CHANGE_EN $end
$upscope $end
$enddefinitions $end
#0
1!
b00000000000000000000000000000000 t
b0 n0
b0000 n1
b00111110 n2
b0 n3
b00000000 n4
b0 n5
b0 n6
b0 n7
b0 n8
b11111111111111111111111111000100 n9
b011 n10
b10 n11
b00111110 n12
b10 n13
b1 n14
#5
#10
1!
b00000000000000000000000000000001 t
b1 n0
b0000 n1
b00111110 n2
b1 n3
b10000000 n4
b0 n5
b1 n6
b1 n7
b1 n8
b11111111111111111111111111000101 n9
b100 n10
b10 n11
b00111110 n12
b10 n13
b0 n14
#15
#20
1!
b00000000000000000000000000000010 t
b1 n0
b0000 n1
b00111110 n2
b0 n3
b10000000 n4
b0 n5
b1 n6
b1 n7
b1 n8
b11111111111111111111111111000110 n9
b000 n10
b10 n11
b00111110 n12
b10 n13
b0 n14
#25
#30
1!
b00000000000000000000000000000011 t
b1 n0
b0000 n1
b00111110 n2
b1 n3
b00000000 n4
b0 n5
b1 n6
b0 n7
b1 n8
b11111111111111111111111111000111 n9
b000 n10
b10 n11
b00111110 n12
b10 n13
b0 n14
#35
#40
1!
b00000000000000000000000000000100 t
b1 n0
b0000 n1
b00111110 n2
b0 n3
b00000000 n4
b0 n5
b1 n6
b0 n7
b1 n8
b11111111111111111111111111001000 n9
b000 n10
b10 n11
b00111110 n12
b10 n13
b0 n14
#45
#50
1!
b00000000000000000000000000000101 t
b1 n0
b0000 n1
b00111110 n2
b1 n3
b10000000 n4
b0 n5
b1 n6
b0 n7
b1 n8
b11111111111111111111111111001001 n9
b000 n10
b10 n11
b00111110 n12
b10 n13
b0 n14
#55
#60
1!
b00000000000000000000000000000110 t
b1 n0
b0000 n1
b00111110 n2
b0 n3
b10000000 n4
b0 n5
b1 n6
b0 n7
b1 n8
b11111111111111111111111111001010 n9
b000 n10
b10 n11
b00111110 n12
b10 n13
b0 n14
#65
#70
1!
b00000000000000000000000000000111 t
b1 n0
b0000 n1
b00111110 n2
b1 n3
b00000000 n4
b0 n5
b1 n6
b0 n7
b1 n8
b11111111111111111111111111001011 n9
b000 n10
b10 n11
b00111110 n12
b10 n13
b0 n14
#75
#80
1!
b00000000000000000000000000001000 t
b1 n0
b0000 n1
b00111110 n2
b0 n3
b00000000 n4
b0 n5
b1 n6
b0 n7
b1 n8
b11111111111111111111111111001100 n9
b000 n10
b10 n11
b00111110 n12
b10 n13
b0 n14
#85
#90
1!
b00000000000000000000000000001001 t
b1 n0
b0000 n1
b00111110 n2
b1 n3
b10000000 n4
b0 n5
b1 n6
b0 n7
b1 n8
b11111111111111111111111111001101 n9
b000 n10
b10 n11
b00111110 n12
b10 n13
b0 n14
#95
#100
1!
b00000000000000000000000000001010 t
b1 n0
b0000 n1
b00111110 n2
b0 n3
b10000000 n4
b0 n5
b1 n6
b0 n7
b1 n8
b11111111111111111111111111001110 n9
b000 n10
b10 n11
b00111110 n12
b10 n13
b0 n14
#105
#110
1!
b00000000000000000000000000001011 t
b1 n0
b0000 n1
b00111110 n2
b1 n3
b00000000 n4
b0 n5
b1 n6
b0 n7
b1 n8
b11111111111111111111111111001111 n9
b000 n10
b10 n11
b00111110 n12
b10 n13
b0 n14
#115
#120
1!
b00000000000000000000000000001100 t
b1 n0
b0000 n1
b00111110 n2
b0 n3
b00000000 n4
b0 n5
b1 n6
b0 n7
b1 n8
b11111111111111111111111111010000 n9
b000 n10
b10 n11
b00111110 n12
b10 n13
b0 n14
#125
#130
1!
b00000000000000000000000000001101 t
b1 n0
b0000 n1
b00111110 n2
b1 n3
b10000000 n4
b0 n5
b1 n6
b0 n7
b1 n8
b11111111111111111111111111010001 n9
b000 n10
b10 n11
b00111110 n12
b10 n13
b0 n14
#135
#140
1!
b00000000000000000000000000001110 t
b1 n0
b0000 n1
b00111110 n2
b0 n3
b10000000 n4
b0 n5
b1 n6
b0 n7
b1 n8
b11111111111111111111111111010010 n9
b000 n10
b10 n11
b00111110 n12
b10 n13
b0 n14
#145
#150
1!
b00000000000000000000000000001111 t
b1 n0
b0000 n1
b00111110 n2
b1 n3
b00000000 n4
b0 n5
b1 n6
b0 n7
b1 n8
b11111111111111111111111111010011 n9
b000 n10
b10 n11
b00111110 n12
b10 n13
b0 n14
#155
#160
1!
b00000000000000000000000000010000 t
b1 n0
b0000 n1
b00111110 n2
b0 n3
b00000000 n4
b0 n5
b1 n6
b0 n7
b1 n8
b11111111111111111111111111010100 n9
b000 n10
b10 n11
b00111110 n12
b10 n13
b0 n14
#165
#170
1!
b00000000000000000000000000010001 t
b1 n0
b0000 n1
b00111110 n2
b1 n3
b10000000 n4
b0 n5
b1 n6
b0 n7
b1 n8
b11111111111111111111111111010101 n9
b000 n10
b10 n11
b00111110 n12
b10 n13
b0 n14
#175
#180
1!
b00000000000000000000000000010010 t
b1 n0
b0000 n1
b00111110 n2
b0 n3
b10000000 n4
b0 n5
b1 n6
b0 n7
b1 n8
b11111111111111111111111111010110 n9
b000 n10
b10 n11
b00111110 n12
b10 n13
b0 n14
#185
#190
1!
b00000000000000000000000000010011 t
b1 n0
b0000 n1
b00111110 n2
b1 n3
b00000000 n4
b0 n5
b1 n6
b0 n7
b1 n8
b11111111111111111111111111010111 n9
b000 n10
b10 n11
b00111110 n12
b10 n13
b0 n14
#195
#200
1!
b00000000000000000000000000010100 t
b1 n0
b0000 n1
b00111110 n2
b0 n3
b00000000 n4
b0 n5
b1 n6
b0 n7
b1 n8
b11111111111111111111111111011000 n9
b000 n10
b10 n11
b00111110 n12
b10 n13
b0 n14
#205
#210
1!
b00000000000000000000000000010101 t
b1 n0
b0000 n1
b00111110 n2
b1 n3
b10000000 n4
b0 n5
b1 n6
b0 n7
b1 n8
b11111111111111111111111111011001 n9
b000 n10
b10 n11
b00111110 n12
b10 n13
b0 n14
#215
#220
1!
b00000000000000000000000000010110 t
b1 n0
b0000 n1
b00111110 n2
b0 n3
b10000000 n4
b0 n5
b1 n6
b0 n7
b1 n8
b11111111111111111111111111011010 n9
b000 n10
b10 n11
b00111110 n12
b10 n13
b0 n14
#225
#230
1!
b00000000000000000000000000010111 t
b1 n0
b0000 n1
b00111110 n2
b1 n3
b00000000 n4
b0 n5
b1 n6
b0 n7
b1 n8
b11111111111111111111111111011011 n9
b000 n10
b10 n11
b00111110 n12
b10 n13
b0 n14
#235
#240
1!
b00000000000000000000000000011000 t
b1 n0
b0000 n1
b00111110 n2
b0 n3
b00000000 n4
b0 n5
b1 n6
b0 n7
b1 n8
b11111111111111111111111111011100 n9
b000 n10
b10 n11
b00111110 n12
b10 n13
b0 n14
#245
#250
1!
b00000000000000000000000000011001 t
b1 n0
b0000 n1
b00111110 n2
b1 n3
b10000000 n4
b0 n5
b1 n6
b0 n7
b1 n8
b11111111111111111111111111011101 n9
b000 n10
b10 n11
b00111110 n12
b10 n13
b0 n14
#255
#260
1!
b00000000000000000000000000011010 t
b1 n0
b0000 n1
b00111110 n2
b0 n3
b10000000 n4
b0 n5
b1 n6
b0 n7
b1 n8
b11111111111111111111111111011110 n9
b000 n10
b10 n11
b00111110 n12
b10 n13
b0 n14
#265
#270
1!
b00000000000000000000000000011011 t
b1 n0
b0000 n1
b00111110 n2
b1 n3
b00000000 n4
b0 n5
b1 n6
b0 n7
b1 n8
b11111111111111111111111111011111 n9
b000 n10
b10 n11
b00111110 n12
b10 n13
b0 n14
#275
#280
1!
b00000000000000000000000000011100 t
b1 n0
b0000 n1
b00111110 n2
b0 n3
b00000000 n4
b0 n5
b1 n6
b0 n7
b1 n8
b11111111111111111111111111100000 n9
b000 n10
b10 n11
b00111110 n12
b10 n13
b0 n14
#285
#290
1!
b00000000000000000000000000011101 t
b1 n0
b0000 n1
b00111110 n2
b1 n3
b10000000 n4
b0 n5
b1 n6
b0 n7
b1 n8
b11111111111111111111111111100001 n9
b000 n10
b10 n11
b00111110 n12
b10 n13
b0 n14
#295
#300
1!
b00000000000000000000000000011110 t
b1 n0
b0000 n1
b00111110 n2
b0 n3
b10000000 n4
b0 n5
b1 n6
b0 n7
b1 n8
b11111111111111111111111111100010 n9
b000 n10
b10 n11
b00111110 n12
b10 n13
b0 n14
#305
#310
1!
b00000000000000000000000000011111 t
b1 n0
b0000 n1
b00111110 n2
b1 n3
b00000000 n4
b0 n5
b1 n6
b0 n7
b1 n8
b11111111111111111111111111100011 n9
b000 n10
b10 n11
b00111110 n12
b10 n13
b0 n14
#315
#320
1!
b00000000000000000000000000100000 t
b1 n0
b0000 n1
b00111110 n2
b0 n3
b00000000 n4
b0 n5
b1 n6
b0 n7
b1 n8
b11111111111111111111111111100100 n9
b000 n10
b10 n11
b00111110 n12
b10 n13
b0 n14
#325
#330
1!
b00000000000000000000000000100001 t
b1 n0
b0000 n1
b00111110 n2
b1 n3
b10000000 n4
b0 n5
b1 n6
b0 n7
b1 n8
b11111111111111111111111111100101 n9
b000 n10
b10 n11
b00111110 n12
b10 n13
b0 n14
#335
#340
1!
b00000000000000000000000000100010 t
b1 n0
b0000 n1
b00111110 n2
b0 n3
b10000000 n4
b0 n5
b1 n6
b0 n7
b1 n8
b11111111111111111111111111100110 n9
b000 n10
b10 n11
b00111110 n12
b10 n13
b0 n14
#345
#350
1!
b00000000000000000000000000100011 t
b1 n0
b0000 n1
b00111110 n2
b1 n3
b00000000 n4
b0 n5
b1 n6
b0 n7
b1 n8
b11111111111111111111111111100111 n9
b000 n10
b10 n11
b00111110 n12
b10 n13
b0 n14
#355
#360
1!
b00000000000000000000000000100100 t
b1 n0
b0000 n1
b00111110 n2
b0 n3
b00000000 n4
b0 n5
b1 n6
b0 n7
b1 n8
b11111111111111111111111111101000 n9
b000 n10
b10 n11
b00111110 n12
b10 n13
b0 n14
#365
#370
1!
b00000000000000000000000000100101 t
b1 n0
b0000 n1
b00111110 n2
b1 n3
b10000000 n4
b0 n5
b1 n6
b0 n7
b1 n8
b11111111111111111111111111101001 n9
b000 n10
b10 n11
b00111110 n12
b10 n13
b0 n14
#375
#380
1!
b00000000000000000000000000100110 t
b1 n0
b0000 n1
b00111110 n2
b0 n3
b10000000 n4
b0 n5
b1 n6
b0 n7
b1 n8
b11111111111111111111111111101010 n9
b000 n10
b10 n11
b00111110 n12
b10 n13
b0 n14
#385
#390
1!
b00000000000000000000000000100111 t
b1 n0
b0000 n1
b00111110 n2
b1 n3
b00000000 n4
b0 n5
b1 n6
b0 n7
b1 n8
b11111111111111111111111111101011 n9
b000 n10
b10 n11
b00111110 n12
b10 n13
b0 n14
#395
#400
1!
b00000000000000000000000000101000 t
b1 n0
b0000 n1
b00111110 n2
b0 n3
b00000000 n4
b0 n5
b1 n6
b0 n7
b1 n8
b11111111111111111111111111101100 n9
b000 n10
b10 n11
b00111110 n12
b10 n13
b0 n14
#405
#410
1!
b00000000000000000000000000101001 t
b1 n0
b0000 n1
b00111110 n2
b1 n3
b10000000 n4
b0 n5
b1 n6
b0 n7
b1 n8
b11111111111111111111111111101101 n9
b000 n10
b10 n11
b00111110 n12
b10 n13
b0 n14
#415
#420
1!
b00000000000000000000000000101010 t
b1 n0
b0000 n1
b00111110 n2
b0 n3
b10000000 n4
b0 n5
b1 n6
b0 n7
b1 n8
b11111111111111111111111111101110 n9
b000 n10
b10 n11
b00111110 n12
b10 n13
b0 n14
#425
#430
1!
b00000000000000000000000000101011 t
b1 n0
b0000 n1
b00111110 n2
b1 n3
b00000000 n4
b0 n5
b1 n6
b0 n7
b1 n8
b11111111111111111111111111101111 n9
b000 n10
b10 n11
b00111110 n12
b10 n13
b0 n14
#435
#440
1!
b00000000000000000000000000101100 t
b1 n0
b0000 n1
b00111110 n2
b0 n3
b00000000 n4
b0 n5
b1 n6
b0 n7
b1 n8
b11111111111111111111111111110000 n9
b000 n10
b10 n11
b00111110 n12
b10 n13
b0 n14
#445
#450
1!
b00000000000000000000000000101101 t
b1 n0
b0000 n1
b00111110 n2
b1 n3
b10000000 n4
b0 n5
b1 n6
b0 n7
b1 n8
b11111111111111111111111111110001 n9
b000 n10
b10 n11
b00111110 n12
b10 n13
b0 n14
#455
#460
1!
b00000000000000000000000000101110 t
b1 n0
b0000 n1
b00111110 n2
b0 n3
b10000000 n4
b0 n5
b1 n6
b0 n7
b1 n8
b11111111111111111111111111110010 n9
b000 n10
b10 n11
b00111110 n12
b10 n13
b0 n14
#465
#470
1!
b00000000000000000000000000101111 t
b1 n0
b0000 n1
b00111110 n2
b1 n3
b00000000 n4
b0 n5
b1 n6
b0 n7
b1 n8
b11111111111111111111111111110011 n9
b000 n10
b10 n11
b00111110 n12
b10 n13
b0 n14
#475
#480
1!
b00000000000000000000000000110000 t
b1 n0
b0000 n1
b00111110 n2
b0 n3
b00000000 n4
b0 n5
b1 n6
b0 n7
b1 n8
b11111111111111111111111111110100 n9
b000 n10
b10 n11
b00111110 n12
b10 n13
b0 n14
#485
#490
1!
b00000000000000000000000000110001 t
b1 n0
b0000 n1
b00111110 n2
b1 n3
b10000000 n4
b0 n5
b1 n6
b0 n7
b1 n8
b11111111111111111111111111110101 n9
b000 n10
b10 n11
b00111110 n12
b10 n13
b0 n14
#495
#500
1!
b00000000000000000000000000110010 t
b1 n0
b0000 n1
b00111110 n2
b0 n3
b10000000 n4
b0 n5
b1 n6
b0 n7
b1 n8
b11111111111111111111111111110110 n9
b000 n10
b10 n11
b00111110 n12
b10 n13
b0 n14
#505
#510
1!
b00000000000000000000000000110011 t
b1 n0
b0000 n1
b00111110 n2
b1 n3
b00000000 n4
b0 n5
b1 n6
b0 n7
b1 n8
b11111111111111111111111111110111 n9
b000 n10
b10 n11
b00111110 n12
b10 n13
b0 n14
#515
#520
1!
b00000000000000000000000000110100 t
b1 n0
b0000 n1
b00111110 n2
b0 n3
b00000000 n4
b0 n5
b1 n6
b0 n7
b1 n8
b11111111111111111111111111111000 n9
b000 n10
b10 n11
b00111110 n12
b10 n13
b0 n14
#525
#530
1!
b00000000000000000000000000110101 t
b1 n0
b0000 n1
b00111110 n2
b1 n3
b00111110 n4
b0 n5
b1 n6
b0 n7
b1 n8
b11111111111111111111111111111001 n9
b000 n10
b10 n11
b00111110 n12
b10 n13
b0 n14
#535
#540
1!
b00000000000000000000000000110110 t
b1 n0
b0000 n1
b00111110 n2
b0 n3
b00111110 n4
b0 n5
b1 n6
b0 n7
b1 n8
b11111111111111111111111111111010 n9
b000 n10
b10 n11
b00111110 n12
b10 n13
b0 n14
#545
#550
1!
b00000000000000000000000000110111 t
b1 n0
b0000 n1
b00111110 n2
b1 n3
b00111110 n4
b0 n5
b1 n6
b0 n7
b1 n8
b11111111111111111111111111111011 n9
b000 n10
b10 n11
b00111110 n12
b10 n13
b0 n14
#555
#560
1!
b00000000000000000000000000111000 t
b1 n0
b0000 n1
b00111110 n2
b0 n3
b00111110 n4
b0 n5
b1 n6
b0 n7
b1 n8
b11111111111111111111111111111100 n9
b000 n10
b10 n11
b00111110 n12
b10 n13
b0 n14
#565
#570
1!
b00000000000000000000000000111001 t
b1 n0
b0000 n1
b00111110 n2
b1 n3
b00111110 n4
b0 n5
b0 n6
b0 n7
b1 n8
b11111111111111111111111111111101 n9
b000 n10
b10 n11
b00111110 n12
b10 n13
b0 n14
#575
#580
1!
b00000000000000000000000000111010 t
b1 n0
b0000 n1
b00111110 n2
b0 n3
b00111110 n4
b0 n5
b0 n6
b0 n7
b1 n8
b11111111111111111111111111111110 n9
b000 n10
b10 n11
b00111110 n12
b10 n13
b0 n14
#585
#590
1!
b00000000000000000000000000111011 t
b1 n0
b0000 n1
b00111110 n2
b1 n3
b00111110 n4
b0 n5
b0 n6
b0 n7
b1 n8
b11111111111111111111111111111111 n9
b000 n10
b10 n11
b00111110 n12
b10 n13
b0 n14
#595
#600
1!
b00000000000000000000000000111100 t
b1 n0
b0000 n1
b00111110 n2
b0 n3
b00111110 n4
b0 n5
b0 n6
b0 n7
b1 n8
b00000000000000000000000000000000 n9
b000 n10
b10 n11
b00111110 n12
b10 n13
b0 n14
#605
#610
1!
b00000000000000000000000000111101 t
b1 n0
b0000 n1
b00111110 n2
b1 n3
b00111110 n4
b0 n5
b1 n6
b0 n7
b1 n8
b00000000000000000000000000000001 n9
b000 n10
b10 n11
b00111110 n12
b10 n13
b0 n14
#615
#620
1!
b00000000000000000000000000111110 t
b1 n0
b0000 n1
b00111110 n2
b0 n3
b00111110 n4
b0 n5
b1 n6
b0 n7
b1 n8
b00000000000000000000000000000000 n9
b000 n10
b10 n11
b00111110 n12
b10 n13
b1 n14
#625
#630
1!
b00000000000000000000000000111111 t
b1 n0
b0000 n1
b00111110 n2
b1 n3
b00111110 n4
b1 n5
b1 n6
b0 n7
b1 n8
b00000000000000000000000000000001 n9
b001 n10
b10 n11
b00111110 n12
b10 n13
b0 n14
#635
#640
1!
b00000000000000000000000001000000 t
b1 n0
b0000 n1
b00111110 n2
b0 n3
b00111110 n4
b1 n5
b1 n6
b1 n7
b1 n8
b00000000000000000000000000000000 n9
b000 n10
b00 n11
b00111110 n12
b01 n13
b0 n14
#645
#650
1!
b00000000000000000000000001000001 t
